{
  "hsaId": "TSTNMT2321000156-105V",
  "givenName": "Nils",
  "middleAndSurname": "Ericsson",
  "systemRoles": [
    "INTYG;Rehab-TSTNMT2321000156-105N"
  ],
  "commissionList": [
    {
      "healthCareUnitHsaId": "TSTNMT2321000156-105N",
      "commissionPurpose": ["STATISTIK"]
    }
  ],
  "fakeProperties": {
    "allowedInApplications": ["RS"],
    "readOnly": true,
    "logins": [
      {
        "forvaldEnhet": "TSTNMT2321000156-105N",
        "beskrivning": "Nils Ericsson (Vårdadmin 1 | Rehabstöd))"
      }
    ]
  }
}
